quaerere_base_common/__init__.py
quaerere_base_common/schema.py
quaerere_base_common-0.1.1.dist-info/LICENSE.txt
quaerere_base_common-0.1.1.dist-info/METADATA
quaerere_base_common-0.1.1.dist-info/WHEEL
quaerere_base_common-0.1.1.dist-info/entry_points.txt
quaerere_base_common-0.1.1.dist-info/top_level.txt
quaerere_base_common-0.1.1.dist-info/RECORD
